{
  "game_id": "3dcfa46f-c1a3-4d90-a813-9e1f25d7bda5",
  "client_id": "3a36f20b-63ca-4e65-ba6c-e86a291a7824",
  "version": "12",
  "versions": [
    "10",
    "12",
    "11"
  ],
  "index": 2,
  "istest": false,
  "game_rounds": 100,
  "sona": "1",
  "experiment_id": "2129",
  "credit_token": "87e1942a617d4527b50309a2467746fd",
  "survey_code": "37467",
  "player2_ability_description": "novice",
  "player2_strategy": "sequence",
  "player1_initial_ability": 0.8,
  "player1_final_ability": 0.8,
  "game_begin_ts": "2021-08-25T20:29:00.701Z",
  "rounds": [
    {
      "round_index": 1,
      "player1_move": "scissors",
      "player2_move": "scissors",
      "player1_ability": 0.8,
      "denoised_player2_move": "scissors",
      "player1_outcome": "tie",
      "player2_outcome": "tie",
      "player1_points": 0,
      "player2_points": 0,
      "player1_points_total": 0,
      "player2_points_total": 0,
      "round_begin_ts": "2021-08-25T20:29:03.855Z",
      "round_results_begin_ts": "2021-08-25T20:29:05.600Z",
      "round_results_end_ts": "2021-08-25T20:29:06.359Z"
    },
    {
      "round_index": 2,
      "player1_move": "scissors",
      "player2_move": "rock",
      "player1_ability": 0.8,
      "denoised_player2_move": "rock",
      "player1_outcome": "loss",
      "player2_outcome": "win",
      "player1_points": -1,
      "player2_points": 3,
      "player1_points_total": 0,
      "player2_points_total": 0,
      "round_begin_ts": "2021-08-25T20:29:06.169Z",
      "round_results_begin_ts": "2021-08-25T20:29:07.920Z",
      "round_results_end_ts": "2021-08-25T20:29:08.416Z"
    },
    {
      "round_index": 3,
      "player1_move": "scissors",
      "player2_move": "paper",
      "player1_ability": 0.8,
      "denoised_player2_move": "paper",
      "player1_outcome": "win",
      "player2_outcome": "loss",
      "player1_points": 3,
      "player2_points": -1,
      "player1_points_total": -1,
      "player2_points_total": 3,
      "round_begin_ts": "2021-08-25T20:29:08.229Z",
      "round_results_begin_ts": "2021-08-25T20:29:09.994Z",
      "round_results_end_ts": "2021-08-25T20:29:10.395Z"
    },
    {
      "round_index": 4,
      "player1_move": "rock",
      "player2_move": "scissors",
      "player1_ability": 0.8,
      "denoised_player2_move": "scissors",
      "player1_outcome": "win",
      "player2_outcome": "loss",
      "player1_points": 3,
      "player2_points": -1,
      "player1_points_total": 2,
      "player2_points_total": 2,
      "round_begin_ts": "2021-08-25T20:29:10.209Z",
      "round_results_begin_ts": "2021-08-25T20:29:11.960Z",
      "round_results_end_ts": "2021-08-25T20:29:12.592Z"
    },
    {
      "round_index": 5,
      "player1_move": "paper",
      "player2_move": "rock",
      "player1_ability": 0.8,
      "denoised_player2_move": "rock",
      "player1_outcome": "win",
      "player2_outcome": "loss",
      "player1_points": 3,
      "player2_points": -1,
      "player1_points_total": 5,
      "player2_points_total": 1,
      "round_begin_ts": "2021-08-25T20:29:12.403Z"
    },
    {
      "round_index": 6,
      "player1_move": "scissors",
      "player2_move": "paper",
      "player1_ability": 0.8,
      "denoised_player2_move": "paper",
      "player1_outcome": "win",
      "player2_outcome": "loss",
      "player1_points": 3,
      "player2_points": -1,
      "player1_points_total": 8,
      "player2_points_total": 0,
      "round_begin_ts": "2021-08-25T20:29:18.965Z",
      "round_results_begin_ts": "2021-08-25T20:29:20.715Z",
      "round_results_end_ts": "2021-08-25T20:29:21.468Z"
    },
    {
      "round_index": 7,
      "player1_move": "rock",
      "player2_move": "scissors",
      "player1_ability": 0.8,
      "denoised_player2_move": "scissors",
      "player1_outcome": "win",
      "player2_outcome": "loss",
      "player1_points": 3,
      "player2_points": -1,
      "player1_points_total": 11,
      "player2_points_total": -1,
      "round_begin_ts": "2021-08-25T20:29:21.285Z",
      "round_results_begin_ts": "2021-08-25T20:29:23.023Z",
      "round_results_end_ts": "2021-08-25T20:29:24.591Z"
    },
    {
      "round_index": 8,
      "player1_move": "paper",
      "player2_move": "paper",
      "player1_ability": 0.8,
      "denoised_player2_move": "rock",
      "player1_outcome": "tie",
      "player2_outcome": "tie",
      "player1_points": 0,
      "player2_points": 0,
      "player1_points_total": 14,
      "player2_points_total": -2,
      "round_begin_ts": "2021-08-25T20:29:24.407Z",
      "round_results_begin_ts": "2021-08-25T20:29:26.234Z",
      "round_results_end_ts": "2021-08-25T20:29:27.113Z"
    },
    {
      "round_index": 9,
      "player1_move": "paper",
      "player2_move": "scissors",
      "player1_ability": 0.8,
      "denoised_player2_move": "scissors",
      "player1_outcome": "loss",
      "player2_outcome": "win",
      "player1_points": -1,
      "player2_points": 3,
      "player1_points_total": 14,
      "player2_points_total": -2,
      "round_begin_ts": "2021-08-25T20:29:26.923Z",
      "round_results_begin_ts": "2021-08-25T20:29:28.686Z",
      "round_results_end_ts": "2021-08-25T20:29:29.531Z"
    },
    {
      "round_index": 10,
      "player1_move": "paper",
      "player2_move": "rock",
      "player1_ability": 0.8,
      "denoised_player2_move": "rock",
      "player1_outcome": "win",
      "player2_outcome": "loss",
      "player1_points": 3,
      "player2_points": -1,
      "player1_points_total": 13,
      "player2_points_total": 1,
      "round_begin_ts": "2021-08-25T20:29:29.477Z"
    },
    {
      "round_index": 11,
      "player1_move": "paper",
      "player2_move": "paper",
      "player1_ability": 0.8,
      "denoised_player2_move": "paper",
      "player1_outcome": "tie",
      "player2_outcome": "tie",
      "player1_points": 0,
      "player2_points": 0,
      "player1_points_total": 16,
      "player2_points_total": 0,
      "round_begin_ts": "2021-08-25T20:29:37.928Z",
      "round_results_begin_ts": "2021-08-25T20:29:39.686Z",
      "round_results_end_ts": "2021-08-25T20:29:40.289Z"
    },
    {
      "round_index": 12,
      "player1_move": "rock",
      "player2_move": "scissors",
      "player1_ability": 0.8,
      "denoised_player2_move": "scissors",
      "player1_outcome": "win",
      "player2_outcome": "loss",
      "player1_points": 3,
      "player2_points": -1,
      "player1_points_total": 16,
      "player2_points_total": 0,
      "round_begin_ts": "2021-08-25T20:29:40.100Z",
      "round_results_begin_ts": "2021-08-25T20:29:41.873Z",
      "round_results_end_ts": "2021-08-25T20:29:43.816Z"
    },
    {
      "round_index": 13,
      "player1_move": "paper",
      "player2_move": "paper",
      "player1_ability": 0.8,
      "denoised_player2_move": "rock",
      "player1_outcome": "tie",
      "player2_outcome": "tie",
      "player1_points": 0,
      "player2_points": 0,
      "player1_points_total": 19,
      "player2_points_total": -1,
      "round_begin_ts": "2021-08-25T20:29:43.628Z",
      "round_results_begin_ts": "2021-08-25T20:29:45.548Z",
      "round_results_end_ts": "2021-08-25T20:29:46.749Z"
    },
    {
      "round_index": 14,
      "player1_move": "rock",
      "player2_move": "scissors",
      "player1_ability": 0.8,
      "denoised_player2_move": "scissors",
      "player1_outcome": "win",
      "player2_outcome": "loss",
      "player1_points": 3,
      "player2_points": -1,
      "player1_points_total": 19,
      "player2_points_total": -1,
      "round_begin_ts": "2021-08-25T20:29:46.573Z",
      "round_results_begin_ts": "2021-08-25T20:29:48.324Z",
      "round_results_end_ts": "2021-08-25T20:29:49.624Z"
    },
    {
      "round_index": 15,
      "player1_move": "paper",
      "player2_move": "rock",
      "player1_ability": 0.8,
      "denoised_player2_move": "rock",
      "player1_outcome": "win",
      "player2_outcome": "loss",
      "player1_points": 3,
      "player2_points": -1,
      "player1_points_total": 22,
      "player2_points_total": -2,
      "round_begin_ts": "2021-08-25T20:29:49.468Z"
    },
    {
      "round_index": 16,
      "player1_move": "paper",
      "player2_move": "paper",
      "player1_ability": 0.8,
      "denoised_player2_move": "paper",
      "player1_outcome": "tie",
      "player2_outcome": "tie",
      "player1_points": 0,
      "player2_points": 0,
      "player1_points_total": 25,
      "player2_points_total": -3,
      "round_begin_ts": "2021-08-25T20:29:57.437Z",
      "round_results_begin_ts": "2021-08-25T20:29:59.180Z",
      "round_results_end_ts": "2021-08-25T20:29:59.978Z"
    },
    {
      "round_index": 17,
      "player1_move": "paper",
      "player2_move": "scissors",
      "player1_ability": 0.8,
      "denoised_player2_move": "scissors",
      "player1_outcome": "loss",
      "player2_outcome": "win",
      "player1_points": -1,
      "player2_points": 3,
      "player1_points_total": 25,
      "player2_points_total": -3,
      "round_begin_ts": "2021-08-25T20:29:59.789Z",
      "round_results_begin_ts": "2021-08-25T20:30:01.526Z",
      "round_results_end_ts": "2021-08-25T20:30:01.946Z"
    },
    {
      "round_index": 18,
      "player1_move": "paper",
      "player2_move": "rock",
      "player1_ability": 0.8,
      "denoised_player2_move": "rock",
      "player1_outcome": "win",
      "player2_outcome": "loss",
      "player1_points": 3,
      "player2_points": -1,
      "player1_points_total": 24,
      "player2_points_total": 0,
      "round_begin_ts": "2021-08-25T20:30:01.809Z",
      "round_results_begin_ts": "2021-08-25T20:30:03.562Z",
      "round_results_end_ts": "2021-08-25T20:30:04.076Z"
    },
    {
      "round_index": 19,
      "player1_move": "scissors",
      "player2_move": "paper",
      "player1_ability": 0.8,
      "denoised_player2_move": "paper",
      "player1_outcome": "win",
      "player2_outcome": "loss",
      "player1_points": 3,
      "player2_points": -1,
      "player1_points_total": 27,
      "player2_points_total": -1,
      "round_begin_ts": "2021-08-25T20:30:03.923Z",
      "round_results_begin_ts": "2021-08-25T20:30:05.800Z",
      "round_results_end_ts": "2021-08-25T20:30:06.522Z"
    },
    {
      "round_index": 20,
      "player1_move": "rock",
      "player2_move": "paper",
      "player1_ability": 0.8,
      "denoised_player2_move": "scissors",
      "player1_outcome": "loss",
      "player2_outcome": "win",
      "player1_points": -1,
      "player2_points": 3,
      "player1_points_total": 30,
      "player2_points_total": -2,
      "round_begin_ts": "2021-08-25T20:30:06.334Z"
    },
    {
      "round_index": 21,
      "player1_move": "rock",
      "player2_move": "scissors",
      "player1_ability": 0.8,
      "denoised_player2_move": "scissors",
      "player1_outcome": "win",
      "player2_outcome": "loss",
      "player1_points": 3,
      "player2_points": -1,
      "player1_points_total": 29,
      "player2_points_total": 1,
      "round_begin_ts": "2021-08-25T20:30:11.784Z",
      "round_results_begin_ts": "2021-08-25T20:30:13.523Z",
      "round_results_end_ts": "2021-08-25T20:30:14.242Z"
    },
    {
      "round_index": 22,
      "player1_move": "paper",
      "player2_move": "rock",
      "player1_ability": 0.8,
      "denoised_player2_move": "rock",
      "player1_outcome": "win",
      "player2_outcome": "loss",
      "player1_points": 3,
      "player2_points": -1,
      "player1_points_total": 32,
      "player2_points_total": 0,
      "round_begin_ts": "2021-08-25T20:30:14.053Z",
      "round_results_begin_ts": "2021-08-25T20:30:15.806Z",
      "round_results_end_ts": "2021-08-25T20:30:16.613Z"
    },
    {
      "round_index": 23,
      "player1_move": "scissors",
      "player2_move": "paper",
      "player1_ability": 0.8,
      "denoised_player2_move": "paper",
      "player1_outcome": "win",
      "player2_outcome": "loss",
      "player1_points": 3,
      "player2_points": -1,
      "player1_points_total": 35,
      "player2_points_total": -1,
      "round_begin_ts": "2021-08-25T20:30:16.425Z",
      "round_results_begin_ts": "2021-08-25T20:30:18.167Z",
      "round_results_end_ts": "2021-08-25T20:30:18.946Z"
    },
    {
      "round_index": 24,
      "player1_move": "rock",
      "player2_move": "scissors",
      "player1_ability": 0.8,
      "denoised_player2_move": "scissors",
      "player1_outcome": "win",
      "player2_outcome": "loss",
      "player1_points": 3,
      "player2_points": -1,
      "player1_points_total": 38,
      "player2_points_total": -2,
      "round_begin_ts": "2021-08-25T20:30:18.758Z",
      "round_results_begin_ts": "2021-08-25T20:30:20.517Z",
      "round_results_end_ts": "2021-08-25T20:30:21.026Z"
    },
    {
      "round_index": 25,
      "player1_move": "paper",
      "player2_move": "rock",
      "player1_ability": 0.8,
      "denoised_player2_move": "rock",
      "player1_outcome": "win",
      "player2_outcome": "loss",
      "player1_points": 3,
      "player2_points": -1,
      "player1_points_total": 41,
      "player2_points_total": -3,
      "round_begin_ts": "2021-08-25T20:30:20.838Z"
    },
    {
      "round_index": 26,
      "player1_move": "scissors",
      "player2_move": "paper",
      "player1_ability": 0.8,
      "denoised_player2_move": "paper",
      "player1_outcome": "win",
      "player2_outcome": "loss",
      "player1_points": 3,
      "player2_points": -1,
      "player1_points_total": 44,
      "player2_points_total": -4,
      "round_begin_ts": "2021-08-25T20:30:26.248Z",
      "round_results_begin_ts": "2021-08-25T20:30:27.989Z",
      "round_results_end_ts": "2021-08-25T20:30:28.445Z"
    },
    {
      "round_index": 27,
      "player1_move": "scissors",
      "player2_move": "rock",
      "player1_ability": 0.8,
      "denoised_player2_move": "scissors",
      "player1_outcome": "loss",
      "player2_outcome": "win",
      "player1_points": -1,
      "player2_points": 3,
      "player1_points_total": 47,
      "player2_points_total": -5,
      "round_begin_ts": "2021-08-25T20:30:28.291Z",
      "round_results_begin_ts": "2021-08-25T20:30:30.027Z",
      "round_results_end_ts": "2021-08-25T20:30:30.274Z"
    },
    {
      "round_index": 28,
      "player1_move": "scissors",
      "player2_move": "paper",
      "player1_ability": 0.8,
      "denoised_player2_move": "paper",
      "player1_outcome": "win",
      "player2_outcome": "loss",
      "player1_points": 3,
      "player2_points": -1,
      "player1_points_total": 46,
      "player2_points_total": -2,
      "round_begin_ts": "2021-08-25T20:30:30.086Z",
      "round_results_begin_ts": "2021-08-25T20:30:31.834Z",
      "round_results_end_ts": "2021-08-25T20:30:32.176Z"
    },
    {
      "round_index": 29,
      "player1_move": "rock",
      "player2_move": "scissors",
      "player1_ability": 0.8,
      "denoised_player2_move": "scissors",
      "player1_outcome": "win",
      "player2_outcome": "loss",
      "player1_points": 3,
      "player2_points": -1,
      "player1_points_total": 49,
      "player2_points_total": -3,
      "round_begin_ts": "2021-08-25T20:30:31.992Z",
      "round_results_begin_ts": "2021-08-25T20:30:33.756Z",
      "round_results_end_ts": "2021-08-25T20:30:34.789Z"
    },
    {
      "round_index": 30,
      "player1_move": "rock",
      "player2_move": "rock",
      "player1_ability": 0.8,
      "denoised_player2_move": "rock",
      "player1_outcome": "tie",
      "player2_outcome": "tie",
      "player1_points": 0,
      "player2_points": 0,
      "player1_points_total": 52,
      "player2_points_total": -4,
      "round_begin_ts": "2021-08-25T20:30:34.602Z"
    },
    {
      "round_index": 31,
      "player1_move": "scissors",
      "player2_move": "paper",
      "player1_ability": 0.8,
      "denoised_player2_move": "paper",
      "player1_outcome": "win",
      "player2_outcome": "loss",
      "player1_points": 3,
      "player2_points": -1,
      "player1_points_total": 52,
      "player2_points_total": -4,
      "round_begin_ts": "2021-08-25T20:30:43.612Z",
      "round_results_begin_ts": "2021-08-25T20:30:45.361Z",
      "round_results_end_ts": "2021-08-25T20:30:45.879Z"
    },
    {
      "round_index": 32,
      "player1_move": "rock",
      "player2_move": "paper",
      "player1_ability": 0.8,
      "denoised_player2_move": "scissors",
      "player1_outcome": "loss",
      "player2_outcome": "win",
      "player1_points": -1,
      "player2_points": 3,
      "player1_points_total": 55,
      "player2_points_total": -5,
      "round_begin_ts": "2021-08-25T20:30:45.691Z",
      "round_results_begin_ts": "2021-08-25T20:30:47.447Z",
      "round_results_end_ts": "2021-08-25T20:30:48.320Z"
    },
    {
      "round_index": 33,
      "player1_move": "scissors",
      "player2_move": "scissors",
      "player1_ability": 0.8,
      "denoised_player2_move": "scissors",
      "player1_outcome": "tie",
      "player2_outcome": "tie",
      "player1_points": 0,
      "player2_points": 0,
      "player1_points_total": 54,
      "player2_points_total": -2,
      "round_begin_ts": "2021-08-25T20:30:48.139Z",
      "round_results_begin_ts": "2021-08-25T20:30:49.873Z",
      "round_results_end_ts": "2021-08-25T20:30:50.627Z"
    },
    {
      "round_index": 34,
      "player1_move": "scissors",
      "player2_move": "rock",
      "player1_ability": 0.8,
      "denoised_player2_move": "rock",
      "player1_outcome": "loss",
      "player2_outcome": "win",
      "player1_points": -1,
      "player2_points": 3,
      "player1_points_total": 54,
      "player2_points_total": -2,
      "round_begin_ts": "2021-08-25T20:30:50.440Z",
      "round_results_begin_ts": "2021-08-25T20:30:52.179Z",
      "round_results_end_ts": "2021-08-25T20:30:52.778Z"
    },
    {
      "round_index": 35,
      "player1_move": "scissors",
      "player2_move": "paper",
      "player1_ability": 0.8,
      "denoised_player2_move": "paper",
      "player1_outcome": "win",
      "player2_outcome": "loss",
      "player1_points": 3,
      "player2_points": -1,
      "player1_points_total": 53,
      "player2_points_total": 1,
      "round_begin_ts": "2021-08-25T20:30:52.590Z"
    },
    {
      "round_index": 36,
      "player1_move": "rock",
      "player2_move": "paper",
      "player1_ability": 0.8,
      "denoised_player2_move": "scissors",
      "player1_outcome": "loss",
      "player2_outcome": "win",
      "player1_points": -1,
      "player2_points": 3,
      "player1_points_total": 56,
      "player2_points_total": 0,
      "round_begin_ts": "2021-08-25T20:30:59.309Z",
      "round_results_begin_ts": "2021-08-25T20:31:01.062Z",
      "round_results_end_ts": "2021-08-25T20:31:01.742Z"
    },
    {
      "round_index": 37,
      "player1_move": "rock",
      "player2_move": "scissors",
      "player1_ability": 0.8,
      "denoised_player2_move": "scissors",
      "player1_outcome": "win",
      "player2_outcome": "loss",
      "player1_points": 3,
      "player2_points": -1,
      "player1_points_total": 55,
      "player2_points_total": 3,
      "round_begin_ts": "2021-08-25T20:31:01.574Z",
      "round_results_begin_ts": "2021-08-25T20:31:03.345Z",
      "round_results_end_ts": "2021-08-25T20:31:04.212Z"
    },
    {
      "round_index": 38,
      "player1_move": "paper",
      "player2_move": "rock",
      "player1_ability": 0.8,
      "denoised_player2_move": "rock",
      "player1_outcome": "win",
      "player2_outcome": "loss",
      "player1_points": 3,
      "player2_points": -1,
      "player1_points_total": 58,
      "player2_points_total": 2,
      "round_begin_ts": "2021-08-25T20:31:04.040Z",
      "round_results_begin_ts": "2021-08-25T20:31:05.793Z",
      "round_results_end_ts": "2021-08-25T20:31:06.850Z"
    },
    {
      "round_index": 39,
      "player1_move": "scissors",
      "player2_move": "paper",
      "player1_ability": 0.8,
      "denoised_player2_move": "paper",
      "player1_outcome": "win",
      "player2_outcome": "loss",
      "player1_points": 3,
      "player2_points": -1,
      "player1_points_total": 61,
      "player2_points_total": 1,
      "round_begin_ts": "2021-08-25T20:31:06.668Z",
      "round_results_begin_ts": "2021-08-25T20:31:08.415Z",
      "round_results_end_ts": "2021-08-25T20:31:09.011Z"
    },
    {
      "round_index": 40,
      "player1_move": "rock",
      "player2_move": "scissors",
      "player1_ability": 0.8,
      "denoised_player2_move": "scissors",
      "player1_outcome": "win",
      "player2_outcome": "loss",
      "player1_points": 3,
      "player2_points": -1,
      "player1_points_total": 64,
      "player2_points_total": 0,
      "round_begin_ts": "2021-08-25T20:31:08.834Z"
    },
    {
      "round_index": 41,
      "player1_move": "paper",
      "player2_move": "rock",
      "player1_ability": 0.8,
      "denoised_player2_move": "rock",
      "player1_outcome": "win",
      "player2_outcome": "loss",
      "player1_points": 3,
      "player2_points": -1,
      "player1_points_total": 67,
      "player2_points_total": -1,
      "round_begin_ts": "2021-08-25T20:31:16.417Z",
      "round_results_begin_ts": "2021-08-25T20:31:18.159Z",
      "round_results_end_ts": "2021-08-25T20:31:18.680Z"
    },
    {
      "round_index": 42,
      "player1_move": "scissors",
      "player2_move": "rock",
      "player1_ability": 0.8,
      "denoised_player2_move": "paper",
      "player1_outcome": "loss",
      "player2_outcome": "win",
      "player1_points": -1,
      "player2_points": 3,
      "player1_points_total": 70,
      "player2_points_total": -2,
      "round_begin_ts": "2021-08-25T20:31:18.523Z",
      "round_results_begin_ts": "2021-08-25T20:31:20.269Z",
      "round_results_end_ts": "2021-08-25T20:31:20.768Z"
    },
    {
      "round_index": 43,
      "player1_move": "scissors",
      "player2_move": "paper",
      "player1_ability": 0.8,
      "denoised_player2_move": "paper",
      "player1_outcome": "win",
      "player2_outcome": "loss",
      "player1_points": 3,
      "player2_points": -1,
      "player1_points_total": 69,
      "player2_points_total": 1,
      "round_begin_ts": "2021-08-25T20:31:20.582Z",
      "round_results_begin_ts": "2021-08-25T20:31:22.357Z",
      "round_results_end_ts": "2021-08-25T20:31:22.826Z"
    },
    {
      "round_index": 44,
      "player1_move": "rock",
      "player2_move": "scissors",
      "player1_ability": 0.8,
      "denoised_player2_move": "scissors",
      "player1_outcome": "win",
      "player2_outcome": "loss",
      "player1_points": 3,
      "player2_points": -1,
      "player1_points_total": 72,
      "player2_points_total": 0,
      "round_begin_ts": "2021-08-25T20:31:22.639Z",
      "round_results_begin_ts": "2021-08-25T20:31:24.394Z",
      "round_results_end_ts": "2021-08-25T20:31:24.992Z"
    },
    {
      "round_index": 45,
      "player1_move": "paper",
      "player2_move": "rock",
      "player1_ability": 0.8,
      "denoised_player2_move": "rock",
      "player1_outcome": "win",
      "player2_outcome": "loss",
      "player1_points": 3,
      "player2_points": -1,
      "player1_points_total": 75,
      "player2_points_total": -1,
      "round_begin_ts": "2021-08-25T20:31:24.805Z"
    },
    {
      "round_index": 46,
      "player1_move": "scissors",
      "player2_move": "paper",
      "player1_ability": 0.8,
      "denoised_player2_move": "paper",
      "player1_outcome": "win",
      "player2_outcome": "loss",
      "player1_points": 3,
      "player2_points": -1,
      "player1_points_total": 78,
      "player2_points_total": -2,
      "round_begin_ts": "2021-08-25T20:31:32.165Z",
      "round_results_begin_ts": "2021-08-25T20:31:33.909Z",
      "round_results_end_ts": "2021-08-25T20:31:35.706Z"
    },
    {
      "round_index": 47,
      "player1_move": "rock",
      "player2_move": "scissors",
      "player1_ability": 0.8,
      "denoised_player2_move": "scissors",
      "player1_outcome": "win",
      "player2_outcome": "loss",
      "player1_points": 3,
      "player2_points": -1,
      "player1_points_total": 81,
      "player2_points_total": -3,
      "round_begin_ts": "2021-08-25T20:31:35.521Z",
      "round_results_begin_ts": "2021-08-25T20:31:37.273Z",
      "round_results_end_ts": "2021-08-25T20:31:37.747Z"
    },
    {
      "round_index": 48,
      "player1_move": "paper",
      "player2_move": "rock",
      "player1_ability": 0.8,
      "denoised_player2_move": "rock",
      "player1_outcome": "win",
      "player2_outcome": "loss",
      "player1_points": 3,
      "player2_points": -1,
      "player1_points_total": 84,
      "player2_points_total": -4,
      "round_begin_ts": "2021-08-25T20:31:37.597Z",
      "round_results_begin_ts": "2021-08-25T20:31:39.365Z",
      "round_results_end_ts": "2021-08-25T20:31:40.090Z"
    },
    {
      "round_index": 49,
      "player1_move": "scissors",
      "player2_move": "paper",
      "player1_ability": 0.8,
      "denoised_player2_move": "paper",
      "player1_outcome": "win",
      "player2_outcome": "loss",
      "player1_points": 3,
      "player2_points": -1,
      "player1_points_total": 87,
      "player2_points_total": -5,
      "round_begin_ts": "2021-08-25T20:31:39.978Z",
      "round_results_begin_ts": "2021-08-25T20:31:41.739Z",
      "round_results_end_ts": "2021-08-25T20:31:42.346Z"
    },
    {
      "round_index": 50,
      "player1_move": "scissors",
      "player2_move": "paper",
      "player1_ability": 0.8,
      "denoised_player2_move": "scissors",
      "player1_outcome": "win",
      "player2_outcome": "loss",
      "player1_points": 3,
      "player2_points": -1,
      "player1_points_total": 90,
      "player2_points_total": -6,
      "round_begin_ts": "2021-08-25T20:31:42.199Z"
    },
    {
      "round_index": 51,
      "player1_move": "rock",
      "player2_move": "scissors",
      "player1_ability": 0.8,
      "denoised_player2_move": "scissors",
      "player1_outcome": "win",
      "player2_outcome": "loss",
      "player1_points": 3,
      "player2_points": -1,
      "player1_points_total": 93,
      "player2_points_total": -7,
      "round_begin_ts": "2021-08-25T20:31:47.789Z",
      "round_results_begin_ts": "2021-08-25T20:31:49.539Z",
      "round_results_end_ts": "2021-08-25T20:31:50.016Z"
    },
    {
      "round_index": 52,
      "player1_move": "paper",
      "player2_move": "rock",
      "player1_ability": 0.8,
      "denoised_player2_move": "rock",
      "player1_outcome": "win",
      "player2_outcome": "loss",
      "player1_points": 3,
      "player2_points": -1,
      "player1_points_total": 96,
      "player2_points_total": -8,
      "round_begin_ts": "2021-08-25T20:31:49.834Z",
      "round_results_begin_ts": "2021-08-25T20:31:51.613Z",
      "round_results_end_ts": "2021-08-25T20:31:52.226Z"
    },
    {
      "round_index": 53,
      "player1_move": "scissors",
      "player2_move": "scissors",
      "player1_ability": 0.8,
      "denoised_player2_move": "paper",
      "player1_outcome": "tie",
      "player2_outcome": "tie",
      "player1_points": 0,
      "player2_points": 0,
      "player1_points_total": 99,
      "player2_points_total": -9,
      "round_begin_ts": "2021-08-25T20:31:52.506Z",
      "round_results_begin_ts": "2021-08-25T20:31:54.250Z",
      "round_results_end_ts": "2021-08-25T20:31:54.986Z"
    },
    {
      "round_index": 54,
      "player1_move": "paper",
      "player2_move": "scissors",
      "player1_ability": 0.8,
      "denoised_player2_move": "rock",
      "player1_outcome": "loss",
      "player2_outcome": "win",
      "player1_points": -1,
      "player2_points": 3,
      "player1_points_total": 99,
      "player2_points_total": -9,
      "round_begin_ts": "2021-08-25T20:31:54.798Z",
      "round_results_begin_ts": "2021-08-25T20:31:56.552Z",
      "round_results_end_ts": "2021-08-25T20:31:57.210Z"
    },
    {
      "round_index": 55,
      "player1_move": "paper",
      "player2_move": "rock",
      "player1_ability": 0.8,
      "denoised_player2_move": "rock",
      "player1_outcome": "win",
      "player2_outcome": "loss",
      "player1_points": 3,
      "player2_points": -1,
      "player1_points_total": 98,
      "player2_points_total": -6,
      "round_begin_ts": "2021-08-25T20:31:57.040Z"
    },
    {
      "round_index": 56,
      "player1_move": "scissors",
      "player2_move": "paper",
      "player1_ability": 0.8,
      "denoised_player2_move": "paper",
      "player1_outcome": "win",
      "player2_outcome": "loss",
      "player1_points": 3,
      "player2_points": -1,
      "player1_points_total": 101,
      "player2_points_total": -7,
      "round_begin_ts": "2021-08-25T20:32:03.436Z",
      "round_results_begin_ts": "2021-08-25T20:32:05.190Z",
      "round_results_end_ts": "2021-08-25T20:32:05.903Z"
    },
    {
      "round_index": 57,
      "player1_move": "rock",
      "player2_move": "scissors",
      "player1_ability": 0.8,
      "denoised_player2_move": "scissors",
      "player1_outcome": "win",
      "player2_outcome": "loss",
      "player1_points": 3,
      "player2_points": -1,
      "player1_points_total": 104,
      "player2_points_total": -8,
      "round_begin_ts": "2021-08-25T20:32:05.715Z",
      "round_results_begin_ts": "2021-08-25T20:32:07.465Z",
      "round_results_end_ts": "2021-08-25T20:32:08.197Z"
    },
    {
      "round_index": 58,
      "player1_move": "paper",
      "player2_move": "scissors",
      "player1_ability": 0.8,
      "denoised_player2_move": "rock",
      "player1_outcome": "loss",
      "player2_outcome": "win",
      "player1_points": -1,
      "player2_points": 3,
      "player1_points_total": 107,
      "player2_points_total": -9,
      "round_begin_ts": "2021-08-25T20:32:08.402Z",
      "round_results_begin_ts": "2021-08-25T20:32:10.140Z",
      "round_results_end_ts": "2021-08-25T20:32:10.818Z"
    },
    {
      "round_index": 59,
      "player1_move": "paper",
      "player2_move": "rock",
      "player1_ability": 0.8,
      "denoised_player2_move": "rock",
      "player1_outcome": "win",
      "player2_outcome": "loss",
      "player1_points": 3,
      "player2_points": -1,
      "player1_points_total": 106,
      "player2_points_total": -6,
      "round_begin_ts": "2021-08-25T20:32:10.631Z",
      "round_results_begin_ts": "2021-08-25T20:32:12.379Z",
      "round_results_end_ts": "2021-08-25T20:32:13.090Z"
    },
    {
      "round_index": 60,
      "player1_move": "scissors",
      "player2_move": "paper",
      "player1_ability": 0.8,
      "denoised_player2_move": "paper",
      "player1_outcome": "win",
      "player2_outcome": "loss",
      "player1_points": 3,
      "player2_points": -1,
      "player1_points_total": 109,
      "player2_points_total": -7,
      "round_begin_ts": "2021-08-25T20:32:12.907Z"
    },
    {
      "round_index": 61,
      "player1_move": "rock",
      "player2_move": "paper",
      "player1_ability": 0.8,
      "denoised_player2_move": "scissors",
      "player1_outcome": "loss",
      "player2_outcome": "win",
      "player1_points": -1,
      "player2_points": 3,
      "player1_points_total": 112,
      "player2_points_total": -8,
      "round_begin_ts": "2021-08-25T20:32:19.492Z",
      "round_results_begin_ts": "2021-08-25T20:32:21.278Z",
      "round_results_end_ts": "2021-08-25T20:32:22.300Z"
    },
    {
      "round_index": 62,
      "player1_move": "rock",
      "player2_move": "scissors",
      "player1_ability": 0.8,
      "denoised_player2_move": "scissors",
      "player1_outcome": "win",
      "player2_outcome": "loss",
      "player1_points": 3,
      "player2_points": -1,
      "player1_points_total": 111,
      "player2_points_total": -5,
      "round_begin_ts": "2021-08-25T20:32:22.542Z",
      "round_results_begin_ts": "2021-08-25T20:32:24.287Z",
      "round_results_end_ts": "2021-08-25T20:32:25.053Z"
    },
    {
      "round_index": 63,
      "player1_move": "paper",
      "player2_move": "rock",
      "player1_ability": 0.8,
      "denoised_player2_move": "rock",
      "player1_outcome": "win",
      "player2_outcome": "loss",
      "player1_points": 3,
      "player2_points": -1,
      "player1_points_total": 114,
      "player2_points_total": -6,
      "round_begin_ts": "2021-08-25T20:32:24.865Z",
      "round_results_begin_ts": "2021-08-25T20:32:26.611Z",
      "round_results_end_ts": "2021-08-25T20:32:27.126Z"
    },
    {
      "round_index": 64,
      "player1_move": "scissors",
      "player2_move": "paper",
      "player1_ability": 0.8,
      "denoised_player2_move": "paper",
      "player1_outcome": "win",
      "player2_outcome": "loss",
      "player1_points": 3,
      "player2_points": -1,
      "player1_points_total": 117,
      "player2_points_total": -7,
      "round_begin_ts": "2021-08-25T20:32:26.939Z",
      "round_results_begin_ts": "2021-08-25T20:32:28.702Z",
      "round_results_end_ts": "2021-08-25T20:32:29.199Z"
    },
    {
      "round_index": 65,
      "player1_move": "rock",
      "player2_move": "scissors",
      "player1_ability": 0.8,
      "denoised_player2_move": "scissors",
      "player1_outcome": "win",
      "player2_outcome": "loss",
      "player1_points": 3,
      "player2_points": -1,
      "player1_points_total": 120,
      "player2_points_total": -8,
      "round_begin_ts": "2021-08-25T20:32:29.015Z"
    },
    {
      "round_index": 66,
      "player1_move": "paper",
      "player2_move": "rock",
      "player1_ability": 0.8,
      "denoised_player2_move": "rock",
      "player1_outcome": "win",
      "player2_outcome": "loss",
      "player1_points": 3,
      "player2_points": -1,
      "player1_points_total": 123,
      "player2_points_total": -9,
      "round_begin_ts": "2021-08-25T20:32:35.920Z",
      "round_results_begin_ts": "2021-08-25T20:32:37.659Z",
      "round_results_end_ts": "2021-08-25T20:32:39.129Z"
    },
    {
      "round_index": 67,
      "player1_move": "scissors",
      "player2_move": "paper",
      "player1_ability": 0.8,
      "denoised_player2_move": "paper",
      "player1_outcome": "win",
      "player2_outcome": "loss",
      "player1_points": 3,
      "player2_points": -1,
      "player1_points_total": 126,
      "player2_points_total": -10,
      "round_begin_ts": "2021-08-25T20:32:38.952Z",
      "round_results_begin_ts": "2021-08-25T20:32:40.735Z",
      "round_results_end_ts": "2021-08-25T20:32:42.166Z"
    },
    {
      "round_index": 68,
      "player1_move": "rock",
      "player2_move": "scissors",
      "player1_ability": 0.8,
      "denoised_player2_move": "scissors",
      "player1_outcome": "win",
      "player2_outcome": "loss",
      "player1_points": 3,
      "player2_points": -1,
      "player1_points_total": 129,
      "player2_points_total": -11,
      "round_begin_ts": "2021-08-25T20:32:42.012Z",
      "round_results_begin_ts": "2021-08-25T20:32:43.761Z",
      "round_results_end_ts": "2021-08-25T20:32:44.510Z"
    },
    {
      "round_index": 69,
      "player1_move": "paper",
      "player2_move": "rock",
      "player1_ability": 0.8,
      "denoised_player2_move": "rock",
      "player1_outcome": "win",
      "player2_outcome": "loss",
      "player1_points": 3,
      "player2_points": -1,
      "player1_points_total": 132,
      "player2_points_total": -12,
      "round_begin_ts": "2021-08-25T20:32:44.325Z",
      "round_results_begin_ts": "2021-08-25T20:32:46.085Z",
      "round_results_end_ts": "2021-08-25T20:32:47.056Z"
    },
    {
      "round_index": 70,
      "player1_move": "scissors",
      "player2_move": "paper",
      "player1_ability": 0.8,
      "denoised_player2_move": "paper",
      "player1_outcome": "win",
      "player2_outcome": "loss",
      "player1_points": 3,
      "player2_points": -1,
      "player1_points_total": 135,
      "player2_points_total": -13,
      "round_begin_ts": "2021-08-25T20:32:46.868Z"
    },
    {
      "round_index": 71,
      "player1_move": "rock",
      "player2_move": "scissors",
      "player1_ability": 0.8,
      "denoised_player2_move": "scissors",
      "player1_outcome": "win",
      "player2_outcome": "loss",
      "player1_points": 3,
      "player2_points": -1,
      "player1_points_total": 138,
      "player2_points_total": -14,
      "round_begin_ts": "2021-08-25T20:32:56.354Z",
      "round_results_begin_ts": "2021-08-25T20:32:58.107Z",
      "round_results_end_ts": "2021-08-25T20:32:59.690Z"
    },
    {
      "round_index": 72,
      "player1_move": "paper",
      "player2_move": "paper",
      "player1_ability": 0.8,
      "denoised_player2_move": "rock",
      "player1_outcome": "tie",
      "player2_outcome": "tie",
      "player1_points": 0,
      "player2_points": 0,
      "player1_points_total": 141,
      "player2_points_total": -15,
      "round_begin_ts": "2021-08-25T20:32:59.503Z",
      "round_results_begin_ts": "2021-08-25T20:33:01.260Z",
      "round_results_end_ts": "2021-08-25T20:33:02.361Z"
    },
    {
      "round_index": 73,
      "player1_move": "scissors",
      "player2_move": "paper",
      "player1_ability": 0.8,
      "denoised_player2_move": "scissors",
      "player1_outcome": "win",
      "player2_outcome": "loss",
      "player1_points": 3,
      "player2_points": -1,
      "player1_points_total": 141,
      "player2_points_total": -15,
      "round_begin_ts": "2021-08-25T20:33:02.173Z",
      "round_results_begin_ts": "2021-08-25T20:33:03.920Z",
      "round_results_end_ts": "2021-08-25T20:33:04.624Z"
    },
    {
      "round_index": 74,
      "player1_move": "rock",
      "player2_move": "scissors",
      "player1_ability": 0.8,
      "denoised_player2_move": "scissors",
      "player1_outcome": "win",
      "player2_outcome": "loss",
      "player1_points": 3,
      "player2_points": -1,
      "player1_points_total": 144,
      "player2_points_total": -16,
      "round_begin_ts": "2021-08-25T20:33:04.441Z",
      "round_results_begin_ts": "2021-08-25T20:33:06.194Z",
      "round_results_end_ts": "2021-08-25T20:33:06.763Z"
    },
    {
      "round_index": 75,
      "player1_move": "paper",
      "player2_move": "paper",
      "player1_ability": 0.8,
      "denoised_player2_move": "rock",
      "player1_outcome": "tie",
      "player2_outcome": "tie",
      "player1_points": 0,
      "player2_points": 0,
      "player1_points_total": 147,
      "player2_points_total": -17,
      "round_begin_ts": "2021-08-25T20:33:06.619Z"
    },
    {
      "round_index": 76,
      "player1_move": "rock",
      "player2_move": "scissors",
      "player1_ability": 0.8,
      "denoised_player2_move": "scissors",
      "player1_outcome": "win",
      "player2_outcome": "loss",
      "player1_points": 3,
      "player2_points": -1,
      "player1_points_total": 147,
      "player2_points_total": -17,
      "round_begin_ts": "2021-08-25T20:33:14.980Z",
      "round_results_begin_ts": "2021-08-25T20:33:16.732Z",
      "round_results_end_ts": "2021-08-25T20:33:17.961Z"
    },
    {
      "round_index": 77,
      "player1_move": "paper",
      "player2_move": "rock",
      "player1_ability": 0.8,
      "denoised_player2_move": "rock",
      "player1_outcome": "win",
      "player2_outcome": "loss",
      "player1_points": 3,
      "player2_points": -1,
      "player1_points_total": 150,
      "player2_points_total": -18,
      "round_begin_ts": "2021-08-25T20:33:17.773Z",
      "round_results_begin_ts": "2021-08-25T20:33:19.541Z",
      "round_results_end_ts": "2021-08-25T20:33:20.188Z"
    },
    {
      "round_index": 78,
      "player1_move": "scissors",
      "player2_move": "scissors",
      "player1_ability": 0.8,
      "denoised_player2_move": "paper",
      "player1_outcome": "tie",
      "player2_outcome": "tie",
      "player1_points": 0,
      "player2_points": 0,
      "player1_points_total": 153,
      "player2_points_total": -19,
      "round_begin_ts": "2021-08-25T20:33:20.001Z",
      "round_results_begin_ts": "2021-08-25T20:33:21.775Z",
      "round_results_end_ts": "2021-08-25T20:33:22.438Z"
    },
    {
      "round_index": 79,
      "player1_move": "scissors",
      "player2_move": "rock",
      "player1_ability": 0.8,
      "denoised_player2_move": "rock",
      "player1_outcome": "loss",
      "player2_outcome": "win",
      "player1_points": -1,
      "player2_points": 3,
      "player1_points_total": 153,
      "player2_points_total": -19,
      "round_begin_ts": "2021-08-25T20:33:22.257Z",
      "round_results_begin_ts": "2021-08-25T20:33:24.010Z",
      "round_results_end_ts": "2021-08-25T20:33:24.515Z"
    },
    {
      "round_index": 80,
      "player1_move": "scissors",
      "player2_move": "paper",
      "player1_ability": 0.8,
      "denoised_player2_move": "paper",
      "player1_outcome": "win",
      "player2_outcome": "loss",
      "player1_points": 3,
      "player2_points": -1,
      "player1_points_total": 152,
      "player2_points_total": -16,
      "round_begin_ts": "2021-08-25T20:33:24.328Z"
    },
    {
      "round_index": 81,
      "player1_move": "scissors",
      "player2_move": "scissors",
      "player1_ability": 0.8,
      "denoised_player2_move": "scissors",
      "player1_outcome": "tie",
      "player2_outcome": "tie",
      "player1_points": 0,
      "player2_points": 0,
      "player1_points_total": 155,
      "player2_points_total": -17,
      "round_begin_ts": "2021-08-25T20:33:32.134Z",
      "round_results_begin_ts": "2021-08-25T20:33:33.867Z",
      "round_results_end_ts": "2021-08-25T20:33:34.687Z"
    },
    {
      "round_index": 82,
      "player1_move": "paper",
      "player2_move": "rock",
      "player1_ability": 0.8,
      "denoised_player2_move": "rock",
      "player1_outcome": "win",
      "player2_outcome": "loss",
      "player1_points": 3,
      "player2_points": -1,
      "player1_points_total": 155,
      "player2_points_total": -17,
      "round_begin_ts": "2021-08-25T20:33:34.500Z",
      "round_results_begin_ts": "2021-08-25T20:33:36.258Z",
      "round_results_end_ts": "2021-08-25T20:33:36.838Z"
    },
    {
      "round_index": 83,
      "player1_move": "rock",
      "player2_move": "paper",
      "player1_ability": 0.8,
      "denoised_player2_move": "paper",
      "player1_outcome": "loss",
      "player2_outcome": "win",
      "player1_points": -1,
      "player2_points": 3,
      "player1_points_total": 158,
      "player2_points_total": -18,
      "round_begin_ts": "2021-08-25T20:33:36.686Z",
      "round_results_begin_ts": "2021-08-25T20:33:38.427Z",
      "round_results_end_ts": "2021-08-25T20:33:39.030Z"
    },
    {
      "round_index": 84,
      "player1_move": "rock",
      "player2_move": "scissors",
      "player1_ability": 0.8,
      "denoised_player2_move": "scissors",
      "player1_outcome": "win",
      "player2_outcome": "loss",
      "player1_points": 3,
      "player2_points": -1,
      "player1_points_total": 157,
      "player2_points_total": -15,
      "round_begin_ts": "2021-08-25T20:33:38.843Z",
      "round_results_begin_ts": "2021-08-25T20:33:40.588Z",
      "round_results_end_ts": "2021-08-25T20:33:41.008Z"
    },
    {
      "round_index": 85,
      "player1_move": "paper",
      "player2_move": "rock",
      "player1_ability": 0.8,
      "denoised_player2_move": "rock",
      "player1_outcome": "win",
      "player2_outcome": "loss",
      "player1_points": 3,
      "player2_points": -1,
      "player1_points_total": 160,
      "player2_points_total": -16,
      "round_begin_ts": "2021-08-25T20:33:40.821Z"
    },
    {
      "round_index": 86,
      "player1_move": "scissors",
      "player2_move": "paper",
      "player1_ability": 0.8,
      "denoised_player2_move": "paper",
      "player1_outcome": "win",
      "player2_outcome": "loss",
      "player1_points": 3,
      "player2_points": -1,
      "player1_points_total": 163,
      "player2_points_total": -17,
      "round_begin_ts": "2021-08-25T20:33:48.918Z",
      "round_results_begin_ts": "2021-08-25T20:33:50.676Z",
      "round_results_end_ts": "2021-08-25T20:33:51.523Z"
    },
    {
      "round_index": 87,
      "player1_move": "rock",
      "player2_move": "scissors",
      "player1_ability": 0.8,
      "denoised_player2_move": "scissors",
      "player1_outcome": "win",
      "player2_outcome": "loss",
      "player1_points": 3,
      "player2_points": -1,
      "player1_points_total": 166,
      "player2_points_total": -18,
      "round_begin_ts": "2021-08-25T20:33:51.348Z",
      "round_results_begin_ts": "2021-08-25T20:33:53.082Z",
      "round_results_end_ts": "2021-08-25T20:33:53.969Z"
    },
    {
      "round_index": 88,
      "player1_move": "paper",
      "player2_move": "rock",
      "player1_ability": 0.8,
      "denoised_player2_move": "rock",
      "player1_outcome": "win",
      "player2_outcome": "loss",
      "player1_points": 3,
      "player2_points": -1,
      "player1_points_total": 169,
      "player2_points_total": -19,
      "round_begin_ts": "2021-08-25T20:33:53.782Z",
      "round_results_begin_ts": "2021-08-25T20:33:55.527Z",
      "round_results_end_ts": "2021-08-25T20:33:56.459Z"
    },
    {
      "round_index": 89,
      "player1_move": "rock",
      "player2_move": "paper",
      "player1_ability": 0.8,
      "denoised_player2_move": "paper",
      "player1_outcome": "loss",
      "player2_outcome": "win",
      "player1_points": -1,
      "player2_points": 3,
      "player1_points_total": 172,
      "player2_points_total": -20,
      "round_begin_ts": "2021-08-25T20:33:56.275Z",
      "round_results_begin_ts": "2021-08-25T20:33:58.033Z",
      "round_results_end_ts": "2021-08-25T20:33:58.842Z"
    },
    {
      "round_index": 90,
      "player1_move": "rock",
      "player2_move": "scissors",
      "player1_ability": 0.8,
      "denoised_player2_move": "scissors",
      "player1_outcome": "win",
      "player2_outcome": "loss",
      "player1_points": 3,
      "player2_points": -1,
      "player1_points_total": 171,
      "player2_points_total": -17,
      "round_begin_ts": "2021-08-25T20:33:58.661Z"
    },
    {
      "round_index": 91,
      "player1_move": "paper",
      "player2_move": "rock",
      "player1_ability": 0.8,
      "denoised_player2_move": "rock",
      "player1_outcome": "win",
      "player2_outcome": "loss",
      "player1_points": 3,
      "player2_points": -1,
      "player1_points_total": 174,
      "player2_points_total": -18,
      "round_begin_ts": "2021-08-25T20:34:06.377Z",
      "round_results_begin_ts": "2021-08-25T20:34:08.122Z",
      "round_results_end_ts": "2021-08-25T20:34:08.630Z"
    },
    {
      "round_index": 92,
      "player1_move": "scissors",
      "player2_move": "paper",
      "player1_ability": 0.8,
      "denoised_player2_move": "paper",
      "player1_outcome": "win",
      "player2_outcome": "loss",
      "player1_points": 3,
      "player2_points": -1,
      "player1_points_total": 177,
      "player2_points_total": -19,
      "round_begin_ts": "2021-08-25T20:34:08.578Z",
      "round_results_begin_ts": "2021-08-25T20:34:10.348Z",
      "round_results_end_ts": "2021-08-25T20:34:10.821Z"
    },
    {
      "round_index": 93,
      "player1_move": "scissors",
      "player2_move": "scissors",
      "player1_ability": 0.8,
      "denoised_player2_move": "scissors",
      "player1_outcome": "tie",
      "player2_outcome": "tie",
      "player1_points": 0,
      "player2_points": 0,
      "player1_points_total": 180,
      "player2_points_total": -20,
      "round_begin_ts": "2021-08-25T20:34:10.633Z",
      "round_results_begin_ts": "2021-08-25T20:34:12.370Z",
      "round_results_end_ts": "2021-08-25T20:34:12.867Z"
    },
    {
      "round_index": 94,
      "player1_move": "paper",
      "player2_move": "rock",
      "player1_ability": 0.8,
      "denoised_player2_move": "rock",
      "player1_outcome": "win",
      "player2_outcome": "loss",
      "player1_points": 3,
      "player2_points": -1,
      "player1_points_total": 180,
      "player2_points_total": -20,
      "round_begin_ts": "2021-08-25T20:34:12.679Z",
      "round_results_begin_ts": "2021-08-25T20:34:14.439Z",
      "round_results_end_ts": "2021-08-25T20:34:14.942Z"
    },
    {
      "round_index": 95,
      "player1_move": "scissors",
      "player2_move": "paper",
      "player1_ability": 0.8,
      "denoised_player2_move": "paper",
      "player1_outcome": "win",
      "player2_outcome": "loss",
      "player1_points": 3,
      "player2_points": -1,
      "player1_points_total": 183,
      "player2_points_total": -21,
      "round_begin_ts": "2021-08-25T20:34:14.755Z"
    },
    {
      "round_index": 96,
      "player1_move": "rock",
      "player2_move": "scissors",
      "player1_ability": 0.8,
      "denoised_player2_move": "scissors",
      "player1_outcome": "win",
      "player2_outcome": "loss",
      "player1_points": 3,
      "player2_points": -1,
      "player1_points_total": 186,
      "player2_points_total": -22,
      "round_begin_ts": "2021-08-25T20:34:21.686Z",
      "round_results_begin_ts": "2021-08-25T20:34:23.419Z",
      "round_results_end_ts": "2021-08-25T20:34:24.529Z"
    },
    {
      "round_index": 97,
      "player1_move": "scissors",
      "player2_move": "rock",
      "player1_ability": 0.8,
      "denoised_player2_move": "rock",
      "player1_outcome": "loss",
      "player2_outcome": "win",
      "player1_points": -1,
      "player2_points": 3,
      "player1_points_total": 189,
      "player2_points_total": -23,
      "round_begin_ts": "2021-08-25T20:34:24.355Z",
      "round_results_begin_ts": "2021-08-25T20:34:26.461Z",
      "round_results_end_ts": "2021-08-25T20:34:28.088Z"
    },
    {
      "round_index": 98,
      "player1_move": "scissors",
      "player2_move": "paper",
      "player1_ability": 0.8,
      "denoised_player2_move": "paper",
      "player1_outcome": "win",
      "player2_outcome": "loss",
      "player1_points": 3,
      "player2_points": -1,
      "player1_points_total": 188,
      "player2_points_total": -20,
      "round_begin_ts": "2021-08-25T20:34:27.901Z",
      "round_results_begin_ts": "2021-08-25T20:34:29.669Z",
      "round_results_end_ts": "2021-08-25T20:34:30.649Z"
    },
    {
      "round_index": 99,
      "player1_move": "rock",
      "player2_move": "scissors",
      "player1_ability": 0.8,
      "denoised_player2_move": "scissors",
      "player1_outcome": "win",
      "player2_outcome": "loss",
      "player1_points": 3,
      "player2_points": -1,
      "player1_points_total": 191,
      "player2_points_total": -21,
      "round_begin_ts": "2021-08-25T20:34:30.460Z",
      "round_results_begin_ts": "2021-08-25T20:34:32.216Z",
      "round_results_end_ts": "2021-08-25T20:34:33.036Z"
    },
    {
      "round_index": 100,
      "player1_move": "paper",
      "player2_move": "paper",
      "player1_ability": 0.8,
      "denoised_player2_move": "rock",
      "player1_outcome": "tie",
      "player2_outcome": "tie",
      "player1_points": 0,
      "player2_points": 0,
      "player1_points_total": 194,
      "player2_points_total": -22,
      "round_begin_ts": "2021-08-25T20:34:32.850Z"
    }
  ],
  "survey_responses": [
    {
      "round_index": 5,
      "slider_1": 6,
      "slider_2": 7
    },
    {
      "round_index": 10,
      "slider_1": 7,
      "slider_2": 7
    },
    {
      "round_index": 15,
      "slider_1": 8,
      "slider_2": 5
    },
    {
      "round_index": 20,
      "slider_1": 7,
      "slider_2": 6
    },
    {
      "round_index": 25,
      "slider_1": 8,
      "slider_2": 6
    },
    {
      "round_index": 30,
      "slider_1": 8,
      "slider_2": 5
    },
    {
      "round_index": 35,
      "slider_1": 7,
      "slider_2": 6
    },
    {
      "round_index": 40,
      "slider_1": 8,
      "slider_2": 6
    },
    {
      "round_index": 45,
      "slider_1": 7,
      "slider_2": 4
    },
    {
      "round_index": 50,
      "slider_1": 8,
      "slider_2": 5
    },
    {
      "round_index": 55,
      "slider_1": 7,
      "slider_2": 5
    },
    {
      "round_index": 60,
      "slider_1": 7,
      "slider_2": 5
    },
    {
      "round_index": 65,
      "slider_1": 8,
      "slider_2": 6
    },
    {
      "round_index": 70,
      "slider_1": 7,
      "slider_2": 5
    },
    {
      "round_index": 75,
      "slider_1": 8,
      "slider_2": 6
    },
    {
      "round_index": 80,
      "slider_1": 7,
      "slider_2": 7
    },
    {
      "round_index": 85,
      "slider_1": 8,
      "slider_2": 6
    },
    {
      "round_index": 90,
      "slider_1": 8,
      "slider_2": 4
    },
    {
      "round_index": 95,
      "slider_1": 8,
      "slider_2": 5
    },
    {
      "round_index": 100,
      "slider_1": 7,
      "slider_2": 6
    }
  ]
}